{
  "ticker": "AVGO",
  "company": "Broadcom Inc",
  "status": "core",
  "sector": "Technology",
  "industry": "Semiconductors",
  "deep_dive": {
    "news_flow": "strong",
    "technicals": "workable",
    "included_reason": "Custom AI ASICs + software; PEG ~0.35 after chip selloff; manual override for D/E above strict screener cutoff.",
    "scores": {
      "news_flow": 80,
      "technicals": 70,
      "fundamentals": 85,
      "composite": 78
    }
  },
  "metrics": {
    "price": 396.81,
    "market_cap": 1887855.34,
    "sales_growth_yoy": 32.29,
    "eps_growth_yoy": 125.17,
    "peg": 0.35,
    "forward_pe": 19.82,
    "gross_margin": 65.66,
    "profit_margin": 38.85,
    "debt_equity": 0.74,
    "recom": 1.32,
    "target_price": 528.6,
    "pe": 66.06
  },
  "technicals": {
    "rsi14": 49.9,
    "sma20_pct": 1.74,
    "sma50_pct": -3.73,
    "sma200_pct": 6.14,
    "perf_ytd": 11.67,
    "from_52w_high_pct": -21.92,
    "beta": 1.47,
    "setup": "Mid-range after selloff; neutral RSI above SMA200",
    "perf_month": -6.04,
    "perf_quarter": -3.29
  },
  "news": {
    "headline_bullets": [
      "Apple custom silicon partnership narrative",
      "Morgan Stanley: AVGO/NVDA best value among chips post-selloff"
    ],
    "next_catalyst": "Next earnings (est. ~September)",
    "catalyst_date": null
  },
  "tags": [
    "ai",
    "asic",
    "semiconductors",
    "software",
    "core",
    "growth",
    "manual-override"
  ],
  "finviz_url": "https://finviz.com/quote.ashx?t=AVGO",
  "deep_dive_path": "deep-dives/AVGO-auto-2026-07-22.md",
  "updated": "2026-07-22",
  "finviz_elite_sync": "2026-07-22T20:53:01"
}
